<?xml version = '1.0' encoding = 'UTF-8'?>
<SegmentOraclev10g class="oracle.dbtools.crest.model.design.storage.oracle.v10g.SegmentOraclev10g" name="Storage1" directorySegmentName="seg_0" id="4F24B20C-0E5D-070E-FE67-F9E678884F3D">
<createdBy>PC</createdBy>
<createdTime>2024-03-12 12:14:05 UTC</createdTime>
<ownerDesignName>db_books</ownerDesignName>
<maxTrans>255</maxTrans>
<scInitialExtent>65536</scInitialExtent>
<scMaxExtents>2147483645</scMaxExtents>
<scNextExtent>1048576</scNextExtent>
</SegmentOraclev10g>